MANIFEST.in
README.rst
setup.py
pecan_mount/__init__.py
pecan_mount/_compat.py
pecan_mount/_tree.py
pecan_mount/util.py
pecan_mount.egg-info/PKG-INFO
pecan_mount.egg-info/SOURCES.txt
pecan_mount.egg-info/dependency_links.txt
pecan_mount.egg-info/entry_points.txt
pecan_mount.egg-info/not-zip-safe
pecan_mount.egg-info/requires.txt
pecan_mount.egg-info/top_level.txt
pecan_mount/tests/__init__.py
pecan_mount/tests/app/__init__.py
pecan_mount/tests/app/app.py
pecan_mount/tests/app/basic.py