Metadata-Version: 1.0
Name: pecan-mount
Version: 0.0.2
Summary: Mount Pecan apps
Home-page: UNKNOWN
Author: Alfredo Deza
Author-email: alfredo [at] deza.pe
License: MIT
Keywords: mount,pecan,wsgi
Platform: UNKNOWN
Classifier: Development Status :: 4 - Beta
Classifier: Intended Audience :: Developers
Classifier: Intended Audience :: System Administrators
Classifier: License :: OSI Approved :: MIT License
Classifier: Operating System :: MacOS :: MacOS X
Classifier: Operating System :: Microsoft :: Windows
Classifier: Operating System :: POSIX
Classifier: Programming Language :: Python
Classifier: Programming Language :: Python :: 2.6
Classifier: Programming Language :: Python :: 2.7
Classifier: Programming Language :: Python :: 3.3
